{"active":true,"archived":false,"automaticallyActive":true,"closed":false,"commentCount":0,"competitive":1,"createdAt":"2026-02-14T23:00:43.957932Z","creationDate":"2026-02-16T09:00:00Z","cyom":false,"deploying":false,"description":"This market refers on the tennis match between Sebastian Ofner and Hugo Gaston in the Lille, scheduled for February 16 at 4:00AM ET.\n\nThis market will resolve to 'Ofner' if Sebastian Ofner advances against Hugo Gaston.\n\nThis market will resolve to 'Gaston' if Hugo Gaston advances against Sebastian Ofner.\n\nIf the match is canceled (not played at all), ends in a tie, or is delayed beyond 7 days from the scheduled date without a winner determined, this market will resolve to 50-50.\n\nIf the match begins but is not completed, and one player advances due to the opponent's retirement, default, or disqualification, this market will resolve to the player who advances.\n\nIf the match ends in a walkover (player withdraws before the start and the other advances automatically), this market will resolve to 50-50.\n\nThe primary resolution source will be official information from the ATP Tour. A consensus of credible reporting may also be used.","enableNegRisk":false,"enableOrderBook":true,"endDate":"2026-02-23T09:00:00Z","eventDate":"2026-02-16","featured":false,"gameId":5184178,"icon":"https://polymarket-upload.s3.us-east-2.amazonaws.com/atp-tour-b4390c4fb8.jpg","id":"209492","image":"https://polymarket-upload.s3.us-east-2.amazonaws.com/atp-tour-b4390c4fb8.jpg","liquidity":1987.8415,"liquidityClob":1987.8415,"markets":[{"acceptingOrders":true,"acceptingOrdersTimestamp":"2026-02-14T23:02:55Z","active":true,"approved":true,"archived":false,"automaticallyActive":true,"bestAsk":0.38,"bestBid":0.36,"clearBookOnStart":true,"clobTokenIds":"[\"1985041226192317006286595544286927843502572408460314354731659090206973099323\", \"42875700003565660848246282090681560655385387682698433367405380499921180988511\"]","closed":false,"competitive":0.9833808634083981,"conditionId":"0x375131d18e8f86760f2db9a11d9162bddde59effdaf6fd4e45cffa3f47e06f71","createdAt":"2026-02-14T23:00:44.058797Z","customLiveness":0,"cyom":false,"deploying":false,"deployingTimestamp":"2026-02-14T23:00:47.507613Z","description":"This market refers on the tennis match between Sebastian Ofner and Hugo Gaston in the Lille, scheduled for February 16 at 4:00AM ET.\n\nThis market will resolve to 'Ofner' if Sebastian Ofner advances against Hugo Gaston.\n\nThis market will resolve to 'Gaston' if Hugo Gaston advances against Sebastian Ofner.\n\nIf the match is canceled (not played at all), ends in a tie, or is delayed beyond 7 days from the scheduled date without a winner determined, this market will resolve to 50-50.\n\nIf the match begins but is not completed, and one player advances due to the opponent's retirement, default, or disqualification, this market will resolve to the player who advances.\n\nIf the match ends in a walkover (player withdraws before the start and the other advances automatically), this market will resolve to 50-50.\n\nThe primary resolution source will be official information from the ATP Tour. A consensus of credible reporting may also be used.","enableOrderBook":true,"endDate":"2026-02-23T09:00:00Z","endDateIso":"2026-02-23","featured":false,"feeType":null,"feesEnabled":false,"funded":false,"gameStartTime":"2026-02-16 19:00:00+00","groupItemThreshold":"0","hasReviewedDates":true,"holdingRewardsEnabled":false,"icon":"https://polymarket-upload.s3.us-east-2.amazonaws.com/atp-tour-b4390c4fb8.jpg","id":"1378819","image":"https://polymarket-upload.s3.us-east-2.amazonaws.com/atp-tour-b4390c4fb8.jpg","lastTradePrice":0.38,"liquidity":"1033.3271","liquidityClob":1033.3271,"liquidityNum":1033.3271,"manualActivation":false,"marketMakerAddress":"","negRisk":false,"negRiskOther":false,"negRiskRequestID":"","new":false,"oneDayPriceChange":-0.135,"oneHourPriceChange":0.005,"orderMinSize":5,"orderPriceMinTickSize":0.01,"outcomePrices":"[\"0.37\", \"0.63\"]","outcomes":"[\"Ofner\", \"Gaston\"]","pagerDutyNotificationEnabled":false,"pendingDeployment":false,"question":"Lille: Sebastian Ofner vs Hugo Gaston","questionID":"0x4c91e97e95bee5bc646ec3ebb13e5eb4aa5696a0daef121ad5007cf281b38ef7","ready":false,"requiresTranslation":false,"resolutionSource":"https://www.atptour.com/en/scores/current","resolvedBy":"0x65070BE91477460D8A7AeEb94ef92fe056C2f2A7","restricted":true,"rewardsMaxSpread":0,"rewardsMinSize":0,"rfqEnabled":false,"secondsDelay":3,"slug":"atp-ofner-gaston-2026-02-16","sportsMarketType":"moneyline","spread":0.02,"startDate":"2026-02-14T23:04:01.208189Z","startDateIso":"2026-02-14","submitted_by":"0x91430CaD2d3975766499717fA0D66A78D814E5c5","umaBond":"500","umaResolutionStatuses":"[]","umaReward":"2","updatedAt":"2026-02-16T01:17:27.664821Z","volume":"990.309339","volume1mo":990.309339,"volume1moClob":990.309339,"volume1wk":990.309339,"volume1wkClob":990.309339,"volume1yr":990.309339,"volume1yrClob":990.309339,"volume24hr":990.309339,"volume24hrClob":990.309339,"volumeClob":990.309339,"volumeNum":990.309339},{"acceptingOrders":true,"acceptingOrdersTimestamp":"2026-02-15T00:10:19Z","active":true,"approved":true,"archived":false,"automaticallyActive":true,"bestAsk":0.97,"bestBid":0.36,"clearBookOnStart":true,"clobTokenIds":"[\"100775242577206430089318379603960150213339273087181694643103014849132588001378\", \"56627432388299176479713555966043529367113921795292276194822305870540690558479\"]","closed":false,"competitive":0.3796636569398136,"conditionId":"0x3a87c915288baf105dcf352ecba6dfe62ef484a57ed9f8b3cd67ef747d12594f","createdAt":"2026-02-15T00:00:34.846238Z","customLiveness":0,"cyom":false,"deploying":false,"deployingTimestamp":"2026-02-15T00:00:56.697964Z","description":"This market refers to the tennis match between Sebastian Ofner and Hugo Gaston in the Lille, scheduled for February 16 2026.\nThis market will resolve to “Ofner” if Sebastian Ofner wins the first set. It will resolve to “Gaston” if Hugo Gaston wins the first set.\nIf the match begins but is not completed, and the first set is concluded with a winner determined, this market will resolve based on that completed set. If the first set is not completed for any reason, this market will resolve 50-50.\nIf the match is canceled (not played at all) or is delayed beyond 7 days from the scheduled date without play beginning, this market will resolve 50-50.\nResolution will be based on official Challenger match statistics.","enableOrderBook":true,"endDate":"2026-02-23T09:00:00Z","endDateIso":"2026-02-23","featured":false,"feeType":null,"feesEnabled":false,"funded":false,"gameStartTime":"2026-02-16 19:00:00+00","groupItemThreshold":"1","groupItemTitle":"Lille: Sebastian Ofner vs Hugo Gaston Set 1 Winner","hasReviewedDates":true,"holdingRewardsEnabled":false,"icon":"https://polymarket-upload.s3.us-east-2.amazonaws.com/atp-tour-b4390c4fb8.jpg","id":"1379139","image":"https://polymarket-upload.s3.us-east-2.amazonaws.com/atp-tour-b4390c4fb8.jpg","liquidity":"93.0326","liquidityClob":93.0326,"liquidityNum":93.0326,"manualActivation":false,"marketMakerAddress":"","negRisk":false,"negRiskOther":false,"negRiskRequestID":"","new":false,"oneDayPriceChange":0.15,"orderMinSize":5,"orderPriceMinTickSize":0.01,"outcomePrices":"[\"0.665\", \"0.335\"]","outcomes":"[\"Ofner\", \"Gaston\"]","pagerDutyNotificationEnabled":false,"pendingDeployment":false,"question":"Set 1 Winner: Ofner vs Gaston","questionID":"0xe2b8e657a2da8bc46a10577617accd8d300b8c89c54933b1c548176df6916081","ready":false,"requiresTranslation":false,"resolutionSource":"https://www.atptour.com/en/scores/current","resolvedBy":"0x65070BE91477460D8A7AeEb94ef92fe056C2f2A7","restricted":true,"rewardsMaxSpread":0,"rewardsMinSize":0,"rfqEnabled":false,"secondsDelay":3,"slug":"atp-ofner-gaston-2026-02-16-first-set-winner-Ofner-vs-Gaston","sportsMarketType":"tennis_first_set_winner","spread":0.61,"startDate":"2026-02-15T00:11:25.303574Z","startDateIso":"2026-02-15","submitted_by":"0x91430CaD2d3975766499717fA0D66A78D814E5c5","umaBond":"500","umaResolutionStatuses":"[]","umaReward":"2","updatedAt":"2026-02-16T01:17:32.538658Z"},{"acceptingOrders":true,"acceptingOrdersTimestamp":"2026-02-15T00:08:07Z","active":true,"approved":true,"archived":false,"automaticallyActive":true,"bestAsk":0.98,"bestBid":0.37,"clearBookOnStart":true,"clobTokenIds":"[\"111435503221210054369616351827005181140256776862868118552534565177609465881187\", \"13458182587602196024441822463612034172783731682004775134335194262125205398602\"]","closed":false,"competitive":0.3784111582777441,"conditionId":"0xba88168d9e711b5eb8963782c426d210749953fd5fa4d019a633bd4e404cfa8d","createdAt":"2026-02-15T00:00:34.937143Z","customLiveness":0,"cyom":false,"deploying":false,"deployingTimestamp":"2026-02-15T00:00:56.695272Z","description":"This market refers to the tennis match between Sebastian Ofner and Hugo Gaston in the Lille, scheduled for February 16 2026.\nThis market will resolve to \"Over\" if the total number of sets completed equals or exceeds 3. Otherwise, it will resolve to \"Under.\"\nA super tie breaker is considered as one (1) set for total set markets.\nIf the match begins but is not completed, this market will resolve 50-50. If the match is canceled before play begins or delayed beyond 7 days from the scheduled date without a result, this market will also resolve 50-50.\nResolution will be based on official Challenger statistics.","enableOrderBook":true,"endDate":"2026-02-23T09:00:00Z","endDateIso":"2026-02-23","featured":false,"feeType":null,"feesEnabled":false,"funded":false,"gameStartTime":"2026-02-16 19:00:00+00","groupItemThreshold":"1","groupItemTitle":"Lille: Sebastian Ofner vs Hugo Gaston Total Sets: O/U 2.5","hasReviewedDates":true,"holdingRewardsEnabled":false,"icon":"https://polymarket-upload.s3.us-east-2.amazonaws.com/atp-tour-b4390c4fb8.jpg","id":"1379140","image":"https://polymarket-upload.s3.us-east-2.amazonaws.com/atp-tour-b4390c4fb8.jpg","line":2.5,"liquidity":"134.403","liquidityClob":134.403,"liquidityNum":134.403,"manualActivation":false,"marketMakerAddress":"","negRisk":false,"negRiskOther":false,"negRiskRequestID":"","new":false,"oneDayPriceChange":0.165,"oneHourPriceChange":-0.005,"orderMinSize":5,"orderPriceMinTickSize":0.01,"outcomePrices":"[\"0.675\", \"0.325\"]","outcomes":"[\"Over 2.5\", \"Under 2.5\"]","pagerDutyNotificationEnabled":false,"pendingDeployment":false,"question":"Ofner vs. Gaston: Total Sets O/U 2.5","questionID":"0xcfce7d366a6b35fb844e83da06f00b2ee2b7b11314cd70abbfc1f9e09ebdcca2","ready":false,"requiresTranslation":false,"resolutionSource":"https://www.atptour.com/en/scores/current","resolvedBy":"0x65070BE91477460D8A7AeEb94ef92fe056C2f2A7","restricted":true,"rewardsMaxSpread":0,"rewardsMinSize":0,"rfqEnabled":false,"secondsDelay":3,"slug":"atp-ofner-gaston-2026-02-16-set-totals-2pt5","sportsMarketType":"tennis_set_totals","spread":0.61,"startDate":"2026-02-15T00:09:13.080916Z","startDateIso":"2026-02-15","submitted_by":"0x91430CaD2d3975766499717fA0D66A78D814E5c5","umaBond":"500","umaResolutionStatuses":"[]","umaReward":"2","updatedAt":"2026-02-16T01:17:37.124049Z"},{"acceptingOrders":true,"acceptingOrdersTimestamp":"2026-02-15T00:10:55Z","active":true,"approved":true,"archived":false,"automaticallyActive":true,"bestAsk":0.63,"bestBid":0.05,"clearBookOnStart":true,"clobTokenIds":"[\"37037854604223351818965598710604512941435999602043606513385622884669965062143\", \"103472115154178054610632147576680998741648409811037025798445868211374924445962\"]","closed":false,"competitive":0.4095163806552262,"conditionId":"0x33f53ef7d072c397d83315d60cfa78820b6004834ce294bda785e51d77541fd6","createdAt":"2026-02-15T00:00:34.843981Z","customLiveness":0,"cyom":false,"deploying":false,"deployingTimestamp":"2026-02-15T00:00:56.701006Z","description":"This market refers to the tennis match between Sebastian Ofner and Hugo Gaston in the Lille, scheduled for February 16 2026.\nThis market will resolve to \"Over\" if the total number of games completed across all sets equals or exceeds 22. Otherwise, it will resolve to \"Under.\"\nAll tiebreaks—including any Champions/Super tiebreak—count as one (1) game toward the total.\nIf the match begins but is not completed, this market will resolve 50-50. If the match is canceled before play begins or delayed beyond 7 days from the scheduled date without a result, this market will also resolve 50-50.\nResolution will be based on official Challenger statistics.","enableOrderBook":true,"endDate":"2026-02-23T09:00:00Z","endDateIso":"2026-02-23","featured":false,"feeType":null,"feesEnabled":false,"funded":false,"gameStartTime":"2026-02-16 19:00:00+00","groupItemThreshold":"1","groupItemTitle":"Lille: Sebastian Ofner vs Hugo Gaston Match O/U 21.5","hasReviewedDates":true,"holdingRewardsEnabled":false,"icon":"https://polymarket-upload.s3.us-east-2.amazonaws.com/atp-tour-b4390c4fb8.jpg","id":"1379138","image":"https://polymarket-upload.s3.us-east-2.amazonaws.com/atp-tour-b4390c4fb8.jpg","line":21.5,"liquidity":"78.6065","liquidityClob":78.6065,"liquidityNum":78.6065,"manualActivation":false,"marketMakerAddress":"","negRisk":false,"negRiskOther":false,"negRiskRequestID":"","new":false,"oneDayPriceChange":-0.17,"orderMinSize":5,"orderPriceMinTickSize":0.01,"outcomePrices":"[\"0.34\", \"0.66\"]","outcomes":"[\"Over\", \"Under\"]","pagerDutyNotificationEnabled":false,"pendingDeployment":false,"question":"Ofner vs. Gaston: Match O/U 21.5","questionID":"0x898050098451a819426e2ee4cdae15e94180bac40b8acbdd23c06af05ecf4b08","ready":false,"requiresTranslation":false,"resolutionSource":"https://www.atptour.com/en/scores/current","resolvedBy":"0x65070BE91477460D8A7AeEb94ef92fe056C2f2A7","restricted":true,"rewardsMaxSpread":0,"rewardsMinSize":0,"rfqEnabled":false,"secondsDelay":3,"slug":"atp-ofner-gaston-2026-02-16-match-total-21pt5","sportsMarketType":"tennis_match_totals","spread":0.58,"startDate":"2026-02-15T00:12:02.178517Z","startDateIso":"2026-02-15","submitted_by":"0x91430CaD2d3975766499717fA0D66A78D814E5c5","umaBond":"500","umaResolutionStatuses":"[]","umaReward":"2","updatedAt":"2026-02-16T01:17:32.124964Z"},{"acceptingOrders":true,"acceptingOrdersTimestamp":"2026-02-15T00:04:49Z","active":true,"approved":true,"archived":false,"automaticallyActive":true,"bestAsk":0.82,"bestBid":0.03,"clearBookOnStart":true,"clobTokenIds":"[\"32950726621851905903395025978802148651631046743359585917687728750238302290966\", \"72478560621740777515774963229313907461837735182481965827115884796323067481712\"]","closed":false,"competitive":0.20882535736482288,"conditionId":"0x26803cbfede05de6ef989c99f5fbea340d5f7e51548efd5156844d42e513aaf2","createdAt":"2026-02-15T00:00:34.941392Z","customLiveness":0,"cyom":false,"deploying":false,"deployingTimestamp":"2026-02-15T00:00:56.70372Z","description":"This market refers to the tennis match between Sebastian Ofner and Hugo Gaston in the Lille, scheduled for February 16 2026.\nThis market will resolve to \"Over\" if the total number of games completed in the first set equals or exceeds 9. Otherwise, it will resolve to \"Under.\"\nAny first-set tiebreak counts as one (1) game toward the total.\nIf the first set is not completed for any reason, this market will resolve 50-50. If the match is canceled before play begins, or delayed beyond 7 days without commencement, this market will also resolve 50-50.\nResolution will be based on official Challenger results.","enableOrderBook":true,"endDate":"2026-02-23T09:00:00Z","endDateIso":"2026-02-23","featured":false,"feeType":null,"feesEnabled":false,"funded":false,"gameStartTime":"2026-02-16 19:00:00+00","groupItemThreshold":"2","groupItemTitle":"Lille: Sebastian Ofner vs Hugo Gaston Set 1 O/U 8.5","hasReviewedDates":true,"holdingRewardsEnabled":false,"icon":"https://polymarket-upload.s3.us-east-2.amazonaws.com/atp-tour-b4390c4fb8.jpg","id":"1379141","image":"https://polymarket-upload.s3.us-east-2.amazonaws.com/atp-tour-b4390c4fb8.jpg","line":8.5,"liquidity":"39.0636","liquidityClob":39.0636,"liquidityNum":39.0636,"manualActivation":false,"marketMakerAddress":"","negRisk":false,"negRiskOther":false,"negRiskRequestID":"","new":false,"oneDayPriceChange":-0.085,"orderMinSize":5,"orderPriceMinTickSize":0.01,"outcomePrices":"[\"0.425\", \"0.575\"]","outcomes":"[\"Over\", \"Under\"]","pagerDutyNotificationEnabled":false,"pendingDeployment":false,"question":"Ofner vs. Gaston: Set 1 Games O/U 8.5","questionID":"0x21901d25413b0c788d2ab4c3b7aeca8d51dd3ad12e632a0ae4c5523947cf06df","ready":false,"requiresTranslation":false,"resolutionSource":"https://www.atptour.com/en/scores/current","resolvedBy":"0x65070BE91477460D8A7AeEb94ef92fe056C2f2A7","restricted":true,"rewardsMaxSpread":0,"rewardsMinSize":0,"rfqEnabled":false,"secondsDelay":3,"slug":"atp-ofner-gaston-2026-02-16-first-set-total-8pt5","sportsMarketType":"tennis_first_set_totals","spread":0.79,"startDate":"2026-02-15T00:05:54.862989Z","startDateIso":"2026-02-15","submitted_by":"0x91430CaD2d3975766499717fA0D66A78D814E5c5","umaBond":"500","umaResolutionStatuses":"[]","umaReward":"2","updatedAt":"2026-02-16T01:17:32.394185Z"},{"acceptingOrders":true,"acceptingOrdersTimestamp":"2026-02-15T00:09:21Z","active":true,"approved":true,"archived":false,"automaticallyActive":true,"bestAsk":0.54,"bestBid":0.46,"clearBookOnStart":true,"clobTokenIds":"[\"14856454237584003233221405334010550184342064782408341041424450456334430538045\", \"4459489674473159841366897581080364502701961049729771094076443239387684664949\"]","closed":false,"competitive":1,"conditionId":"0xd1198ac301dc1237428cbf505eeb9ab766ca8790849c09fe0113abf1512b4e03","createdAt":"2026-02-15T00:00:35.02358Z","customLiveness":0,"cyom":false,"deploying":false,"deployingTimestamp":"2026-02-15T00:00:56.708129Z","description":"This market refers to the tennis match between Sebastian Ofner and Hugo Gaston in the Lille, scheduled for February 16 2026.\nThis market will resolve to \"Over\" if the total number of games completed across all sets equals or exceeds 23. Otherwise, it will resolve to \"Under.\"\nAll tiebreaks—including any Champions/Super tiebreak—count as one (1) game toward the total.\nIf the match begins but is not completed, this market will resolve 50-50. If the match is canceled before play begins or delayed beyond 7 days from the scheduled date without a result, this market will also resolve 50-50.\nResolution will be based on official Challenger statistics.","enableOrderBook":true,"endDate":"2026-02-23T09:00:00Z","endDateIso":"2026-02-23","featured":false,"feeType":null,"feesEnabled":false,"funded":false,"gameStartTime":"2026-02-16 19:00:00+00","groupItemThreshold":"1","groupItemTitle":"Lille: Sebastian Ofner vs Hugo Gaston Match O/U 22.5","hasReviewedDates":true,"holdingRewardsEnabled":false,"icon":"https://polymarket-upload.s3.us-east-2.amazonaws.com/atp-tour-b4390c4fb8.jpg","id":"1379142","image":"https://polymarket-upload.s3.us-east-2.amazonaws.com/atp-tour-b4390c4fb8.jpg","line":22.5,"liquidity":"471.3463","liquidityClob":471.3463,"liquidityNum":471.3463,"manualActivation":false,"marketMakerAddress":"","negRisk":false,"negRiskOther":false,"negRiskRequestID":"","new":false,"oneDayPriceChange":-0.01,"orderMinSize":5,"orderPriceMinTickSize":0.01,"outcomePrices":"[\"0.5\", \"0.5\"]","outcomes":"[\"Over\", \"Under\"]","pagerDutyNotificationEnabled":false,"pendingDeployment":false,"question":"Ofner vs. Gaston: Match O/U 22.5","questionID":"0x015e1dd854574d2fa76268e621daa3877d7a473d1be162f2c89c3fd90c61414e","ready":false,"requiresTranslation":false,"resolutionSource":"https://www.atptour.com/en/scores/current","resolvedBy":"0x65070BE91477460D8A7AeEb94ef92fe056C2f2A7","restricted":true,"rewardsMaxSpread":0,"rewardsMinSize":0,"rfqEnabled":false,"secondsDelay":3,"slug":"atp-ofner-gaston-2026-02-16-match-total-22pt5","sportsMarketType":"tennis_match_totals","spread":0.08,"startDate":"2026-02-15T00:10:26.875334Z","startDateIso":"2026-02-15","submitted_by":"0x91430CaD2d3975766499717fA0D66A78D814E5c5","umaBond":"500","umaResolutionStatuses":"[]","umaReward":"2","updatedAt":"2026-02-16T01:17:31.924433Z"},{"acceptingOrders":true,"acceptingOrdersTimestamp":"2026-02-15T00:03:01Z","active":true,"approved":true,"archived":false,"automaticallyActive":true,"bestAsk":0.98,"bestBid":0.03,"clearBookOnStart":true,"clobTokenIds":"[\"105835140904882525406854342711652281346864351414335427492579216755384839612742\", \"29139733426856197086725099634311693441754743126241605211119388116335396772212\"]","closed":false,"competitive":0.04999875003124922,"conditionId":"0xa3e8940edef17b91fb542322258fa60067015d6c6aaf35ba16d4720c29c702d9","createdAt":"2026-02-15T00:00:35.044568Z","customLiveness":0,"cyom":false,"deploying":false,"deployingTimestamp":"2026-02-15T00:00:56.710121Z","description":"This market refers to the tennis match between Sebastian Ofner and Hugo Gaston in the Lille, scheduled for February 16 2026.\nThis market will resolve to \"Over\" if the total number of games completed in the first set equals or exceeds 10. Otherwise, it will resolve to \"Under.\"\nAny first-set tiebreak counts as one (1) game toward the total.\nIf the first set is not completed for any reason, this market will resolve 50-50. If the match is canceled before play begins, or delayed beyond 7 days without commencement, this market will also resolve 50-50.\nResolution will be based on official Challenger results.","enableOrderBook":true,"endDate":"2026-02-23T09:00:00Z","endDateIso":"2026-02-23","featured":false,"feeType":null,"feesEnabled":false,"funded":false,"gameStartTime":"2026-02-16 19:00:00+00","groupItemThreshold":"2","groupItemTitle":"Lille: Sebastian Ofner vs Hugo Gaston Set 1 O/U 9.5","hasReviewedDates":true,"holdingRewardsEnabled":false,"icon":"https://polymarket-upload.s3.us-east-2.amazonaws.com/atp-tour-b4390c4fb8.jpg","id":"1379143","image":"https://polymarket-upload.s3.us-east-2.amazonaws.com/atp-tour-b4390c4fb8.jpg","line":9.5,"liquidity":"3.6534","liquidityClob":3.6534,"liquidityNum":3.6534,"manualActivation":false,"marketMakerAddress":"","negRisk":false,"negRiskOther":false,"negRiskRequestID":"","new":false,"oneHourPriceChange":-0.005,"orderMinSize":5,"orderPriceMinTickSize":0.01,"outcomePrices":"[\"0.505\", \"0.495\"]","outcomes":"[\"Over\", \"Under\"]","pagerDutyNotificationEnabled":false,"pendingDeployment":false,"question":"Ofner vs. Gaston: Set 1 Games O/U 9.5","questionID":"0xc95be3b318fa2cc3343a6cb149540c3746951234adc369d07b0c68162cc92784","ready":false,"requiresTranslation":false,"resolutionSource":"https://www.atptour.com/en/scores/current","resolvedBy":"0x65070BE91477460D8A7AeEb94ef92fe056C2f2A7","restricted":true,"rewardsMaxSpread":0,"rewardsMinSize":0,"rfqEnabled":false,"secondsDelay":3,"slug":"atp-ofner-gaston-2026-02-16-first-set-total-9pt5","sportsMarketType":"tennis_first_set_totals","spread":0.95,"startDate":"2026-02-15T00:04:08.0514Z","startDateIso":"2026-02-15","submitted_by":"0x91430CaD2d3975766499717fA0D66A78D814E5c5","umaBond":"500","umaResolutionStatuses":"[]","umaReward":"2","updatedAt":"2026-02-16T01:17:34.283724Z"},{"acceptingOrders":true,"acceptingOrdersTimestamp":"2026-02-15T00:06:21Z","active":true,"approved":true,"archived":false,"automaticallyActive":true,"bestAsk":0.98,"bestBid":0.4,"clearBookOnStart":true,"clobTokenIds":"[\"71448264590995788968230791021648044516504216192361633156716959773244111285122\", \"76363161981837076114792382751216329441543399051647553211481270018503419411531\"]","closed":false,"competitive":0.40536627738635267,"conditionId":"0xa68de6693500ea1bd9a1548ab2c11e6ab5dbfa0ea84d355ce33aeca26d5fcfdd","createdAt":"2026-02-15T00:00:35.129034Z","customLiveness":0,"cyom":false,"deploying":false,"deployingTimestamp":"2026-02-15T00:00:56.746059Z","description":"This market refers to the tennis match between Sebastian Ofner and Hugo Gaston in the Lille, scheduled for February 16 2026.\nThis market will resolve to \"Over\" if the total number of games completed across all sets equals or exceeds 24. Otherwise, it will resolve to \"Under.\"\nAll tiebreaks—including any Champions/Super tiebreak—count as one (1) game toward the total.\nIf the match begins but is not completed, this market will resolve 50-50. If the match is canceled before play begins or delayed beyond 7 days from the scheduled date without a result, this market will also resolve 50-50.\nResolution will be based on official Challenger statistics.","enableOrderBook":true,"endDate":"2026-02-23T09:00:00Z","endDateIso":"2026-02-23","featured":false,"feeType":null,"feesEnabled":false,"funded":false,"gameStartTime":"2026-02-16 19:00:00+00","groupItemThreshold":"1","groupItemTitle":"Lille: Sebastian Ofner vs Hugo Gaston Match O/U 23.5","hasReviewedDates":true,"holdingRewardsEnabled":false,"icon":"https://polymarket-upload.s3.us-east-2.amazonaws.com/atp-tour-b4390c4fb8.jpg","id":"1379144","image":"https://polymarket-upload.s3.us-east-2.amazonaws.com/atp-tour-b4390c4fb8.jpg","line":23.5,"liquidity":"82.7555","liquidityClob":82.7555,"liquidityNum":82.7555,"manualActivation":false,"marketMakerAddress":"","negRisk":false,"negRiskOther":false,"negRiskRequestID":"","new":false,"oneDayPriceChange":0.175,"oneHourPriceChange":-0.005,"orderMinSize":5,"orderPriceMinTickSize":0.01,"outcomePrices":"[\"0.69\", \"0.31\"]","outcomes":"[\"Over\", \"Under\"]","pagerDutyNotificationEnabled":false,"pendingDeployment":false,"question":"Ofner vs. Gaston: Match O/U 23.5","questionID":"0x40b8ec0f124dbee6c0e23fe222ca7fa1ec3def5834828a36ca52e95394936de6","ready":false,"requiresTranslation":false,"resolutionSource":"https://www.atptour.com/en/scores/current","resolvedBy":"0x65070BE91477460D8A7AeEb94ef92fe056C2f2A7","restricted":true,"rewardsMaxSpread":0,"rewardsMinSize":0,"rfqEnabled":false,"secondsDelay":3,"slug":"atp-ofner-gaston-2026-02-16-match-total-23pt5","sportsMarketType":"tennis_match_totals","spread":0.58,"startDate":"2026-02-15T00:07:26.968797Z","startDateIso":"2026-02-15","submitted_by":"0x91430CaD2d3975766499717fA0D66A78D814E5c5","umaBond":"500","umaResolutionStatuses":"[]","umaReward":"2","updatedAt":"2026-02-16T01:17:34.793339Z"},{"acceptingOrders":true,"acceptingOrdersTimestamp":"2026-02-15T00:04:53Z","active":true,"approved":true,"archived":false,"automaticallyActive":true,"bestAsk":0.99,"bestBid":0.25,"clearBookOnStart":true,"clobTokenIds":"[\"114385671245446784667095347193335241510227219605147211541371948633935863834288\", \"88523112758501061845119515738022349544115857176261516479606684427342643770693\"]","closed":false,"competitive":0.25630914826498424,"conditionId":"0x85fff97aff47507ea2559c0a5a3a9c72b646f83bd799f34a086350160c5428a6","createdAt":"2026-02-15T00:00:35.148519Z","customLiveness":0,"cyom":false,"deploying":false,"deployingTimestamp":"2026-02-15T00:00:56.749021Z","description":"This market refers to the tennis match between Sebastian Ofner and Hugo Gaston in the Lille, scheduled for February 16 2026.\nThis market will resolve to \"Over\" if the total number of games completed in the first set equals or exceeds 11. Otherwise, it will resolve to \"Under.\"\nAny first-set tiebreak counts as one (1) game toward the total.\nIf the first set is not completed for any reason, this market will resolve 50-50. If the match is canceled before play begins, or delayed beyond 7 days without commencement, this market will also resolve 50-50.\nResolution will be based on official Challenger results.","enableOrderBook":true,"endDate":"2026-02-23T09:00:00Z","endDateIso":"2026-02-23","featured":false,"feeType":null,"feesEnabled":false,"funded":false,"gameStartTime":"2026-02-16 19:00:00+00","groupItemThreshold":"2","groupItemTitle":"Lille: Sebastian Ofner vs Hugo Gaston Set 1 O/U 10.5","hasReviewedDates":true,"holdingRewardsEnabled":false,"icon":"https://polymarket-upload.s3.us-east-2.amazonaws.com/atp-tour-b4390c4fb8.jpg","id":"1379145","image":"https://polymarket-upload.s3.us-east-2.amazonaws.com/atp-tour-b4390c4fb8.jpg","line":10.5,"liquidity":"51.6535","liquidityClob":51.6535,"liquidityNum":51.6535,"manualActivation":false,"marketMakerAddress":"","negRisk":false,"negRiskOther":false,"negRiskRequestID":"","new":false,"oneDayPriceChange":0.105,"orderMinSize":5,"orderPriceMinTickSize":0.01,"outcomePrices":"[\"0.62\", \"0.38\"]","outcomes":"[\"Over\", \"Under\"]","pagerDutyNotificationEnabled":false,"pendingDeployment":false,"question":"Ofner vs. Gaston: Set 1 Games O/U 10.5","questionID":"0xb913137eee9b2912121f1f90ccff9dd572ebb2e1319f846cf0dfa0b64d34ac92","ready":false,"requiresTranslation":false,"resolutionSource":"https://www.atptour.com/en/scores/current","resolvedBy":"0x65070BE91477460D8A7AeEb94ef92fe056C2f2A7","restricted":true,"rewardsMaxSpread":0,"rewardsMinSize":0,"rfqEnabled":false,"secondsDelay":3,"slug":"atp-ofner-gaston-2026-02-16-first-set-total-10pt5","sportsMarketType":"tennis_first_set_totals","spread":0.74,"startDate":"2026-02-15T00:05:59.991716Z","startDateIso":"2026-02-15","submitted_by":"0x91430CaD2d3975766499717fA0D66A78D814E5c5","umaBond":"500","umaResolutionStatuses":"[]","umaReward":"2","updatedAt":"2026-02-16T01:17:11.2703Z"}],"negRisk":false,"negRiskAugmented":false,"new":false,"openInterest":0,"pendingDeployment":false,"requiresTranslation":false,"resolutionSource":"https://www.atptour.com/en/scores/current","restricted":true,"series":[{"active":true,"archived":false,"closed":false,"commentCount":1336,"createdAt":"2025-10-07T17:08:06.009679Z","featured":false,"icon":"","id":"10365","image":"","liquidity":4061347.15251,"recurrence":"daily","requiresTranslation":false,"restricted":true,"seriesType":"single","slug":"atp","ticker":"atp","title":"ATP","updatedAt":"2026-02-16T01:17:59.150894Z","volume":1066637.508502,"volume24hr":2869962.816607999}],"seriesSlug":"atp","showAllOutcomes":true,"showMarketImages":false,"slug":"atp-ofner-gaston-2026-02-16","sport":{"createdAt":"2025-11-07T21:08:59.561861Z","id":45,"image":"https://polymarket-upload.s3.us-east-2.amazonaws.com/atp-tour-b4390c4fb8.jpg","ordering":"home","resolution":"https://www.atptour.com/en/scores/current","series":"10365","sport":"atp","tags":"1,864,100639,101232"},"startDate":"2026-02-14T23:04:04.90439Z","startTime":"2026-02-16T19:00:00Z","tags":[{"createdAt":"2024-01-12T19:45:09.677Z","forceShow":false,"id":"864","label":"Tennis","publishedAt":"2024-01-12 19:45:09.662+00","requiresTranslation":false,"slug":"tennis","updatedAt":"2026-02-06T20:10:12.802044Z"},{"createdAt":"2023-10-24T22:37:50.31Z","forceHide":true,"forceShow":false,"id":"1","label":"Sports","publishedAt":"2023-10-24 22:37:50.296+00","requiresTranslation":false,"slug":"sports","updatedAt":"2026-02-06T20:05:01.908169Z","updatedBy":15},{"createdAt":"2024-09-23T22:41:37.670714Z","forceShow":false,"id":"100639","label":"Games","requiresTranslation":false,"slug":"games","updatedAt":"2026-02-06T20:08:42.474229Z"}],"teams":[{"abbreviation":"gaston","color":"#A02020","createdAt":"2025-11-01T04:00:02.764912Z","id":183168,"league":"atp","logo":"https://polymarket-upload.s3.us-east-2.amazonaws.com/country-flags/fra.png","name":"Hugo Gaston","providerId":795298,"record":"0-0","updatedAt":"2025-11-05T00:19:38.766912Z"},{"abbreviation":"ofner","createdAt":"2026-01-11T16:46:25.182659Z","id":229592,"league":"atp","logo":"https://polymarket-upload.s3.us-east-2.amazonaws.com/country-flags/aut.png","name":"Sebastian Ofner","providerId":453754,"record":"0-0"}],"ticker":"atp-ofner-gaston-2026-02-16","title":"Lille: Sebastian Ofner vs Hugo Gaston","updatedAt":"2026-02-16T01:17:52.237302Z","volume":990.309339,"volume1mo":990.309339,"volume1wk":990.309339,"volume1yr":990.309339,"volume24hr":990.309339}