{
  "entity": "event",
  "event_id": "136681",
  "folder_rule": "event.createdAt (fallback: max(markets[].published_at))",
  "folder_dt_utc": "2026-01-01T12:01:49.420830Z",
  "event_createdAt": "2026-01-01T12:01:49.42083Z",
  "event_creationDate": "2026-01-01T12:10:53.475063Z",
  "event_startDate": "2026-01-01T12:10:53.475066Z",
  "event_endDate": "2026-01-02T12:15:00Z",
  "event_updatedAt": "2026-01-02T12:15:56.794182Z",
  "markets_len": 1,
  "market_ids": [
    "1080714"
  ],
  "series_len": 1,
  "series_ids": [
    "10423"
  ],
  "series_slug": "sol-up-or-down-15m"
}