{
  "conditionId": "0x59ba869ea3a2ef0e676eb7848d1b4d73894f757dc319d95a9f61b7aa966b44be",
  "entity": "market",
  "folder_dt_utc": "2026-02-01T18:00:23.300243Z",
  "folder_rule": "market.createdAt (fallback: market.published_at)",
  "market_closedTime": null,
  "market_createdAt": "2026-02-01T18:00:23.300243Z",
  "market_endDate": "2026-02-09T07:00:00Z",
  "market_id": "1314595",
  "market_startDate": "2026-02-01T18:03:49.285596Z",
  "market_updatedAt": "2026-02-02T01:15:17.50127Z",
  "question": "Badosa vs. Sasnovich: Match O/U 23.5",
  "slug": "wta-badosa-sasnovi-2026-02-02-match-total-23pt5"
}