{
  "conditionId": "0x65773bab25be52b1b51f37a3c20e1de7f938ccf5ddc1917cc351bf47b6f5eba2",
  "entity": "market",
  "folder_dt_utc": "2026-02-19T21:07:10.107120Z",
  "folder_rule": "market.createdAt (fallback: market.published_at)",
  "market_closedTime": "2026-02-21 01:00:54+00",
  "market_createdAt": "2026-02-19T21:07:10.10712Z",
  "market_endDate": "2026-02-21T01:00:00Z",
  "market_id": "1399366",
  "market_startDate": "2026-02-19T21:08:28.803428Z",
  "market_updatedAt": "2026-02-21T12:29:27.716269Z",
  "question": "Solana Up or Down - February 20, 4:00PM-8:00PM ET",
  "slug": "sol-updown-4h-1771621200"
}