{
  "conditionId": "0xbf704022e008646f9ca1e183c8e489f49f3ea24a9725277492b0aaa910625d1a",
  "entity": "market",
  "folder_dt_utc": "2026-02-21T06:00:26.968272Z",
  "folder_rule": "market.createdAt (fallback: market.published_at)",
  "market_closedTime": null,
  "market_createdAt": "2026-02-21T06:00:26.968272Z",
  "market_endDate": "2026-02-28T20:30:00Z",
  "market_id": "1406086",
  "market_startDate": "2026-02-21T06:04:56.960177Z",
  "market_updatedAt": "2026-02-21T12:29:21.344548Z",
  "question": "Garland vs. You: Match O/U 23.5",
  "slug": "wta-garland-you-2026-02-21-match-total-23pt5"
}