{
  "conditionId": "0xb023b5b5c2518d0ece93fc35f8518415d4a417169f8feb4d8f1eabdc52d3251a",
  "entity": "market",
  "folder_dt_utc": "2026-02-16T05:00:14.839806Z",
  "folder_rule": "market.createdAt (fallback: market.published_at)",
  "market_closedTime": null,
  "market_createdAt": "2026-02-16T05:00:14.839806Z",
  "market_endDate": "2026-02-23T05:00:00Z",
  "market_id": "1384057",
  "market_startDate": "2026-02-16T05:02:58.720983Z",
  "market_updatedAt": "2026-02-19T18:39:13.459814Z",
  "question": "Will XRP dip to $1.30 February 16-22?",
  "slug": "will-xrp-dip-to-1pt3-february-16-22"
}