{
  "conditionId": "0xadb036386510287628a61b0dc03590cf16d9e6982f6dbd2434d8cd4099f5cae5",
  "entity": "market",
  "folder_dt_utc": "2026-02-05T02:50:04.031535Z",
  "folder_rule": "market.createdAt (fallback: market.published_at)",
  "market_closedTime": null,
  "market_createdAt": "2026-02-05T02:50:04.031535Z",
  "market_endDate": "2026-02-06T01:00:00Z",
  "market_id": "1337500",
  "market_startDate": "2026-02-05T02:52:36.375417Z",
  "market_updatedAt": "2026-02-05T06:43:14.504647Z",
  "question": "Total Kills Over/Under 46.5 in Game 1?",
  "slug": "dota2-ts8-rnx-2026-02-05-game1-kill-over-46pt5"
}