{
  "conditionId": "0xdd43dae161c969374b2ca714ed38ac8a665bcb40fbbd56af0492f564bd98e3c9",
  "entity": "market",
  "folder_dt_utc": "2026-02-17T00:00:46.992313Z",
  "folder_rule": "market.createdAt (fallback: market.published_at)",
  "market_closedTime": null,
  "market_createdAt": "2026-02-17T00:00:46.992313Z",
  "market_endDate": "2026-02-24T11:00:00Z",
  "market_id": "1387300",
  "market_startDate": "2026-02-17T00:05:44.896534Z",
  "market_updatedAt": "2026-02-17T12:41:16.742818Z",
  "question": "Skatov vs. Hemery: Set 1 Games O/U 10.5",
  "slug": "atp-skatov-hemery-2026-02-17-first-set-total-10pt5"
}