{
  "conditionId": "0x01a66d998c8f6dd4899bd3f3eef96351c16ea188ea8b569232db509d46a5158a",
  "entity": "market",
  "folder_dt_utc": "2026-02-09T03:00:14.068504Z",
  "folder_rule": "market.createdAt (fallback: market.published_at)",
  "market_closedTime": "2026-02-11 05:19:29+00",
  "market_createdAt": "2026-02-09T03:00:14.068504Z",
  "market_endDate": "2026-02-11T04:00:00Z",
  "market_id": "1357912",
  "market_startDate": "2026-02-09T03:03:07.519517Z",
  "market_updatedAt": "2026-02-11T18:51:23.003269Z",
  "question": "XRP Up or Down - February 10, 10PM ET",
  "slug": "xrp-up-or-down-february-10-10pm-et"
}