{
  "conditionId": "0x584a5cc6c75fe5b809f13840f09d543c6b206715139cc12764cad3114e25b8ce",
  "entity": "market",
  "folder_dt_utc": "2026-01-12T07:31:48.221124Z",
  "folder_rule": "market.createdAt (fallback: market.published_at)",
  "market_closedTime": null,
  "market_createdAt": "2026-01-12T07:31:48.221124Z",
  "market_endDate": "2026-01-13T07:45:00Z",
  "market_id": "1165864",
  "market_startDate": "2026-01-12T07:32:16.123041Z",
  "market_updatedAt": "2026-01-13T06:23:16.05901Z",
  "question": "Bitcoin Up or Down - January 13, 2:30AM-2:45AM ET",
  "slug": "btc-updown-15m-1768289400"
}