{
  "entity": "market",
  "market_id": "1113462",
  "folder_rule": "market.createdAt (fallback: market.published_at)",
  "folder_dt_utc": "2026-01-05T11:41:47.907479Z",
  "market_createdAt": "2026-01-05T11:41:47.907479Z",
  "market_updatedAt": null,
  "market_startDate": "2026-01-05T11:41:47Z",
  "market_endDate": "2026-01-06T11:40:00Z",
  "market_closedTime": null,
  "conditionId": "0x41353dcb0c713f338b616f2f91a53bb0216e222c28a1ef9e44820f799823c2c8",
  "slug": "sol-updown-5m-1767699300",
  "question": "Solana Up or Down - January 6, 6:35AM-6:40AM ET"
}