{
  "conditionId": "0x22f45f1db0a5268104c5a9e57972ab6bbf790b7bcd9a38513b61dffa2ba516ef",
  "entity": "market",
  "folder_dt_utc": "2026-01-12T14:50:32.173951Z",
  "folder_rule": "market.createdAt (fallback: market.published_at)",
  "market_closedTime": null,
  "market_createdAt": "2026-01-12T14:50:32.173951Z",
  "market_endDate": "2026-01-17T00:00:00Z",
  "market_id": "1167490",
  "market_startDate": "2026-01-13T00:43:44.007482Z",
  "market_updatedAt": "2026-01-15T01:03:13.118179Z",
  "question": "Will the total number of TSA passengers for January 17 be between 2,400,000 and 2,500,000?",
  "slug": "will-the-total-number-of-tsa-passengers-for-january-17-be-between-2400000-and-2500000"
}