{
  "conditionId": "0x96ca59068b43985b92f685d8921caebe195ab3ad659801d779357cbd8fb70bf7",
  "entity": "market",
  "folder_dt_utc": "2026-01-19T13:30:03.632658Z",
  "folder_rule": "market.createdAt (fallback: market.published_at)",
  "market_closedTime": null,
  "market_createdAt": "2026-01-19T13:30:03.632658Z",
  "market_endDate": "2026-01-20T17:30:00Z",
  "market_id": "1219898",
  "market_startDate": "2026-01-19T13:31:02.868975Z",
  "market_updatedAt": "2026-01-19T18:21:33.796117Z",
  "question": "Games Total: O/U 2.5",
  "slug": "cs2-biga-navij1-2026-01-20-total-games-2pt5"
}