{
  "conditionId": "0x03ae4f13040c6e477c7958ea04e67a08591729c98b2364794e353bd67ce8d986",
  "entity": "market",
  "folder_dt_utc": "2026-01-17T08:30:15.288570Z",
  "folder_rule": "market.createdAt (fallback: market.published_at)",
  "market_closedTime": null,
  "market_createdAt": "2026-01-17T08:30:15.28857Z",
  "market_endDate": "2026-01-20T15:00:00Z",
  "market_id": "1205134",
  "market_startDate": "2026-01-17T08:31:44.130168Z",
  "market_updatedAt": "2026-01-19T12:27:51.220081Z",
  "question": "Counter-Strike: MOUZ NXT vs BASEMENT BOYS (BO3) - European Pro League Series 4 Group D",
  "slug": "cs2-mouzn-bmb-2026-01-20"
}