{
  "conditionId": "0x77d6e39145bc2a06e318beaf0e468d4f9df914375e4a3db4f8949e9cc5364029",
  "entity": "market",
  "folder_dt_utc": "2026-01-13T17:59:30.446287Z",
  "folder_rule": "market.createdAt (fallback: market.published_at)",
  "market_closedTime": "2026-01-14 08:47:28+00",
  "market_createdAt": "2026-01-13T17:59:30.446287Z",
  "market_endDate": "2026-02-28T00:00:00Z",
  "market_id": "1176560",
  "market_startDate": "2026-01-13T18:09:31.365394Z",
  "market_updatedAt": "2026-01-15T06:17:02.154726Z",
  "question": "Will Mamdani say \"Crisis\" during the next NYC Mayor's Office announcement?",
  "slug": "will-mamdani-say-crisis-during-the-next-nyc-mayors-office-announcement"
}