{
  "conditionId": "0x0bc5424ba6757bf38556daac4cd8da48337dc5bcd877d21925bcaf368b88e420",
  "entity": "market",
  "folder_dt_utc": "2026-01-30T23:00:44.733577Z",
  "folder_rule": "market.createdAt (fallback: market.published_at)",
  "market_closedTime": "2026-02-02 01:14:40+00",
  "market_createdAt": "2026-01-30T23:00:44.733577Z",
  "market_endDate": "2026-02-08T09:00:00Z",
  "market_id": "1301932",
  "market_startDate": "2026-01-30T23:06:17.629845Z",
  "market_updatedAt": "2026-02-03T01:15:13.589065Z",
  "question": "Transylvania Open: Mayar Sherif vs Oleksandra Oliynykova",
  "slug": "wta-sherif-oliynyk-2026-02-01"
}