{
  "conditionId": "0x570d62058ef7b961d4448e0a73871ba5d1cc6c4818595cd0450a90491698eea2",
  "entity": "market",
  "folder_dt_utc": "2026-01-24T09:08:32.463028Z",
  "folder_rule": "market.createdAt (fallback: market.published_at)",
  "market_closedTime": null,
  "market_createdAt": "2026-01-24T09:08:32.463028Z",
  "market_endDate": "2026-01-25T09:15:00Z",
  "market_id": "1257087",
  "market_startDate": "2026-01-24T09:08:58.304269Z",
  "market_updatedAt": "2026-01-25T06:17:37.987164Z",
  "question": "Bitcoin Up or Down - January 25, 4:00AM-4:15AM ET",
  "slug": "btc-updown-15m-1769331600"
}