{
  "conditionId": "0xc3f5d147e18d5cf7fb11a8d0e1e836658c345663812a0e21fc1a9a83238caa0c",
  "entity": "market",
  "folder_dt_utc": "2026-01-28T10:00:16.047723Z",
  "folder_rule": "market.createdAt (fallback: market.published_at)",
  "market_closedTime": null,
  "market_createdAt": "2026-01-28T10:00:16.047723Z",
  "market_endDate": "2026-01-29T01:00:00Z",
  "market_id": "1281942",
  "market_startDate": "2026-01-28T10:03:17.081796Z",
  "market_updatedAt": "2026-01-28T18:25:06.274479Z",
  "question": "Counter-Strike: BASEMENT BOYS vs ENRAGE (BO1) - ESEA Advanced Europe Regular Season",
  "slug": "cs2-bmb-enr1-2026-01-28"
}