{
  "conditionId": "0x19bed03c13af082203e56d23434dde6f5e33a0b0bcae8f568cedab0718043d6b",
  "entity": "market",
  "folder_dt_utc": "2026-01-31T00:10:27.931837Z",
  "folder_rule": "market.createdAt (fallback: market.published_at)",
  "market_closedTime": null,
  "market_createdAt": "2026-01-31T00:10:27.931837Z",
  "market_endDate": "2026-01-31T20:00:00Z",
  "market_id": "1302791",
  "market_startDate": "2026-01-31T00:13:07.446638Z",
  "market_updatedAt": "2026-01-31T12:25:03.577042Z",
  "question": "Brandon Miller: Points O/U 20.5",
  "slug": "nba-sas-cha-2026-01-31-points-brandon-miller-20pt5"
}